hotdate/__init__.py
hotdate-0.4.5.dist-info/top_level.txt
hotdate-0.4.5.dist-info/METADATA
hotdate-0.4.5.dist-info/DESCRIPTION.rst
hotdate-0.4.5.dist-info/pydist.json
hotdate-0.4.5.dist-info/WHEEL
hotdate-0.4.5.dist-info/RECORD
