Metadata-Version: 2.0
Name: hotdate
Version: 0.4.5
Summary: Intuitive date formatting.
Home-page: http://pypi.python.org/pypi/hotdate/
Author: Samuel "mansam" Lucidi
Author-email: mansam@csh.rit.edu
License: LICENSE
Platform: UNKNOWN
Requires-Dist: six
Requires-Dist: python-dateutil
Requires-Dist: freezegun
